Chromify/Chromify.py
Chromify/Color.py
Chromify/Converter.py
Chromify/__init__.py
Chromify/ext/MassiveColors.py
Chromify/ext/__init__.py
lib/Chromify.py
lib/Color.py
lib/Converter.py
lib/__init__.py
lib/main.py
Chromify-1.1.8.dist-info/LICENSE
Chromify-1.1.8.dist-info/METADATA
Chromify-1.1.8.dist-info/WHEEL
Chromify-1.1.8.dist-info/top_level.txt
Chromify-1.1.8.dist-info/RECORD
