Metadata-Version: 2.1
Name: Chromify
Version: 1.1.8
Summary: Colorful Terminal Prints
Home-page: https://github.com/plaraje/Chromify
Author: Plaraje
Author-email: mat.demoya@gmail.com
Classifier: Programming Language :: Python :: 3
Classifier: Programming Language :: Python :: 3.6
Classifier: Programming Language :: Python :: 3.7
Classifier: Programming Language :: Python :: 3.8
Classifier: Programming Language :: Python :: 3.9
Classifier: Programming Language :: Python :: 3.10
License-File: LICENSE
